bovespaparser/__init__.py
bovespaparser/bovespaparser.py
bovespaparser/parsingutils.py
bovespaparser-0.6.5.dist-info/METADATA
bovespaparser-0.6.5.dist-info/WHEEL
bovespaparser-0.6.5.dist-info/top_level.txt
bovespaparser-0.6.5.dist-info/RECORD
