Metadata-Version: 2.1
Name: bovespaparser
Version: 0.6.5
Summary: Bovespa's historical series files parser.
Home-page: http://pypi.python.org/pypi/bovespaparser
Author: Roberto Haddock Lobo
Author-email: rhlobo+stockexperiments@gmail.com
License: MIT
Keywords: bovespa,parser,historical,series,cotahist,stock
Platform: UNKNOWN
Classifier: Programming Language :: Python
Classifier: Programming Language :: Python :: 2.7
Classifier: Programming Language :: Python :: 3.8
Classifier: Development Status :: 4 - Beta
Classifier: Environment :: Other Environment
Classifier: Intended Audience :: Developers
Classifier: Intended Audience :: Financial and Insurance Industry
Classifier: License :: OSI Approved :: MIT License
Classifier: Operating System :: OS Independent
Classifier: Topic :: Software Development :: Libraries :: Python Modules
Classifier: Topic :: Office/Business :: Financial :: Investment
